hiertunehub/__init__.py
hiertunehub/search_space.py
hiertunehub/tuner.py
hiertunehub/utils.py
hiertunehub/version.py
hiertunehub/viz.py
hiertunehub-0.2.1.dist-info/licenses/LICENSE
hiertunehub-0.2.1.dist-info/METADATA
hiertunehub-0.2.1.dist-info/WHEEL
hiertunehub-0.2.1.dist-info/top_level.txt
hiertunehub-0.2.1.dist-info/RECORD
