Metadata-Version: 2.4
Name: HierTuneHub
Version: 0.2.1
Summary: A Python package to provide unified interface for hierarchical hyperparameter optimization
Author-email: Yikun Jiang <jiangyikun9663@gmail.com>
License: MIT License
Project-URL: Source, https://github.com/ItsYikunJiang/HierTuneHub
Keywords: hyperparameter optimization,search space,unified interface
Requires-Python: >=3.8
License-File: LICENSE
Requires-Dist: PyYAML
Provides-Extra: test
Requires-Dist: pytest; extra == "test"
Provides-Extra: opt
Requires-Dist: hyperopt; extra == "opt"
Requires-Dist: optuna; extra == "opt"
Requires-Dist: flaml; extra == "opt"
Dynamic: license-file
